Kuat/__init__.py
hadziq-0.1.0.dist-info/METADATA
hadziq-0.1.0.dist-info/WHEEL
hadziq-0.1.0.dist-info/top_level.txt
hadziq-0.1.0.dist-info/RECORD
